jaction/EL.py
jaction/__init__.py
jaction-0.1.1.dist-info/LICENSE
jaction-0.1.1.dist-info/METADATA
jaction-0.1.1.dist-info/WHEEL
jaction-0.1.1.dist-info/top_level.txt
jaction-0.1.1.dist-info/RECORD
