Metadata-Version: 2.1
Name: jaction
Version: 0.1.1
Summary: Principle of least action with JAX
Home-page: https://github.com/adxsrc/jaction
Author: Chi-kwan Chan
Author-email: chanc@arizona.edu
License: UNKNOWN
Platform: UNKNOWN
Requires-Python: >=3.7
License-File: LICENSE
Requires-Dist: xaj (==0.1.1)
